MANIFEST.in
readme.md
requirements.txt
setup.py
TemporaryStorage/__init__.py
TemporaryStorage/__main__.py
TemporaryStorage.egg-info/PKG-INFO
TemporaryStorage.egg-info/SOURCES.txt
TemporaryStorage.egg-info/dependency_links.txt
TemporaryStorage.egg-info/requires.txt
TemporaryStorage.egg-info/top_level.txt
TemporaryStorage/providers/__init__.py
TemporaryStorage/providers/0x0/__init__.py
TemporaryStorage/providers/cockfile/__init__.py
TemporaryStorage/providers/fileditch/__init__.py
TemporaryStorage/providers/oshi/__init__.py
TemporaryStorage/providers/pomflainla/__init__.py
TemporaryStorage/providers/qu/__init__.py
TemporaryStorage/providers/telegraph/__init__.py
TemporaryStorage/providers/transfer/__init__.py
TemporaryStorage/providers/uguu/__init__.py
TemporaryStorage/providers/x0/__init__.py