Metadata-Version: 2.1
Name: TemporaryStorage
Version: 2022.1.31.2
Summary: A simple library for temporary storage of small files.
Home-page: https://github.com/ulbwazhine/TemporaryStorage
Author: Ulbwazhine
Author-email: ulbwa@icloud.com
License: MIT
Platform: UNKNOWN
